rtl/timer.v
// this is used to count down
 module timer #(
    parameter WIDTH  = 8,           // counter bit-width
    parameter PERIOD = 30           // default count value
)(
    input  wire             clk,
    input  wire             rst_n,  // async active-low reset
    input  wire             en,     // enable counting
    input  wire             load,   // reload counter
    input  wire [WIDTH-1:0] period, // dynamic period (used when load=1)
    output reg              done    // pulses high for 1 clk when count hits 0
);
 
    reg [WIDTH-1:0] count;
 
    always @(posedge clk or negedge rst_n) begin
        if (!rst_n) begin
            count <= PERIOD - 1;
            done  <= 1'b0;
        end else begin
            done <= 1'b0; // default: no pulse
 
            if (load) begin
                count <= period - 1;
            end else if (en) begin
                if (count == 0) begin
                    count <= PERIOD - 1; // auto-reload
                    done  <= 1'b1;
                end else begin
                    count <= count - 1;
                end
            end
        end
    end
 
endmodule

tb/tb_timer.v
`timescale 1ns/1ps

module tb_timer;

//inputs
reg clk;
reg rst_n;
reg en;
reg load;
reg [7:0] period;
// outputs
wire done;

  timer #(
        .WIDTH  (8),
        .PERIOD (10)       // short period so easier to simulate
  ) dut(
    .clk(clk),
    .rst_n(rst_n),
    .en (en),
    .load (load),
    .period (period),
    .done(done)
  );

  initial clk=0;
  always #5 clk=~clk;//created a clock with time period 10ns(5ns on and 5ns off)
// task
 task apply_reset;
        begin
            rst_n  = 0;
            en     = 0;
            load   = 0;
            period = 0;
            repeat(4) @(posedge clk); // hold reset for 4 ticks
            rst_n = 1;                // release reset
            @(posedge clk);           // wait one more tick to settle
        end
    endtask
 
    // ---- task: wait N ticks ----
    task wait_ticks;
        input integer n;
        integer i;
        begin
            for(i = 0; i < n; i = i + 1)
                @(posedge clk);
        end
    endtask
  // To check every time done pulsed
  always @(posedge clk) begin
    if (done)
    $display("[%0t] Done pusled ",$time);
  end
// test stimulus
  initial begin
    $dumpfile("tb_timer.vcd");
    $dumpvars(0,tb_timer);

    $display("  Scenario 1: Reset ");
  apply_reset;
  if (done !== 1'b0)
            $display("FAIL: done should be 0 after reset");
        else
            $display("PASS: done is 0 after reset");




    $display("   Scenario 2:normal countdown");
    // check the difference between the done as it shloud be 10 ticks
    apply_reset;
    en=1;
    repeat(25) @(posedge clk)begin
        if(done)
        $display("done is high at %0t",$time);
    end
    en=0;



    $display("   Scenario 3:Enable pause");
    apply_reset;
    en=1;
    repeat(4) @(posedge clk);
    $display("paused");
    en=0;
    wait_ticks(5);
    $display("resuming");
    en=1;
    wait_ticks(10);


    $display("Scenario 4: reset mid count");
    apply_reset;
    en=1;
    wait_ticks(4);
     $display("   Applying reset mid-count...");
        rst_n = 0;              // reset while counting
        @(posedge clk);
        rst_n = 1;
        if (done !== 1'b0)
            $display("FAIL: done should be 0 after mid-count reset");
        else
            $display("PASS: reset mid-count works correctly");
        wait_ticks(5);
 
        $display("\n=== ALL SCENARIOS DONE ===\n");
        $finish;
    end
endmodule

sim/tb_timer.vcd
$date
	Sat May 23 20:11:29 2026
$end
$version
	Icarus Verilog
$end
$timescale
	1ps
$end
$scope module tb_timer $end
$var wire 1 ! done $end
$var reg 1 " clk $end
$var reg 1 # en $end
$var reg 1 $ load $end
$var reg 8 % period [7:0] $end
$var reg 1 & rst_n $end
$scope module dut $end
$var wire 1 " clk $end
$var wire 1 # en $end
$var wire 1 $ load $end
$var wire 8 ' period [7:0] $end
$var wire 1 & rst_n $end
$var parameter 32 ( PERIOD $end
$var parameter 32 ) WIDTH $end
$var reg 8 * count [7:0] $end
$var reg 1 ! done $end
$upscope $end
$scope task apply_reset $end
$upscope $end
$scope task wait_ticks $end
$var integer 32 + i [31:0] $end
$var integer 32 , n [31:0] $end
$upscope $end
$upscope $end
$enddefinitions $end
$comment Show the parameter values. $end
$dumpall
b1000 )
b1010 (
$end
#0
$dumpvars
bx ,
bx +
b1001 *
b0 '
0&
b0 %
0$
0#
0"
0!
$end
#5000
1"
#10000
0"
#15000
1"
#20000
0"
#25000
1"
#30000
0"
#35000
1&
1"
#40000
0"
#45000
0&
1"
#50000
0"
#55000
1"
#60000
0"
#65000
1"
#70000
0"
#75000
1"
#80000
0"
#85000
1&
1"
#90000
0"
#95000
b1000 *
1#
1"
#100000
0"
#105000
b111 *
1"
#110000
0"
#115000
b110 *
1"
#120000
0"
#125000
b101 *
1"
#130000
0"
#135000
b100 *
1"
#140000
0"
#145000
b11 *
1"
#150000
0"
#155000
b10 *
1"
#160000
0"
#165000
b1 *
1"
#170000
0"
#175000
b0 *
1"
#180000
0"
#185000
1!
b1001 *
1"
#190000
0"
#195000
b1000 *
0!
1"
#200000
0"
#205000
b111 *
1"
#210000
0"
#215000
b110 *
1"
#220000
0"
#225000
b101 *
1"
#230000
0"
#235000
b100 *
1"
#240000
0"
#245000
b11 *
1"
#250000
0"
#255000
b10 *
1"
#260000
0"
#265000
b1 *
1"
#270000
0"
#275000
b0 *
1"
#280000
0"
#285000
1!
b1001 *
1"
#290000
0"
#295000
b1000 *
0!
1"
#300000
0"
#305000
b111 *
1"
#310000
0"
#315000
b110 *
1"
#320000
0"
#325000
b101 *
1"
#330000
0"
#335000
b100 *
1"
#340000
0"
#345000
b1001 *
0&
0#
1"
#350000
0"
#355000
1"
#360000
0"
#365000
1"
#370000
0"
#375000
1"
#380000
0"
#385000
1&
1"
#390000
0"
#395000
b1000 *
1#
1"
#400000
0"
#405000
b111 *
1"
#410000
0"
#415000
b110 *
1"
#420000
0"
#425000
b101 *
1"
#430000
0"
#435000
b0 +
b101 ,
0#
1"
#440000
0"
#445000
b1 +
1"
#450000
0"
#455000
b10 +
1"
#460000
0"
#465000
b11 +
1"
#470000
0"
#475000
b100 +
1"
#480000
0"
#485000
b100 *
b1010 ,
1#
b0 +
1"
#490000
0"
#495000
b11 *
b1 +
1"
#500000
0"
#505000
b10 *
b10 +
1"
#510000
0"
#515000
b1 *
b11 +
1"
#520000
0"
#525000
b0 *
b100 +
1"
#530000
0"
#535000
1!
b1001 *
b101 +
1"
#540000
0"
#545000
b1000 *
0!
b110 +
1"
#550000
0"
#555000
b111 *
b111 +
1"
#560000
0"
#565000
b110 *
b1000 +
1"
#570000
0"
#575000
b101 *
b1001 +
1"
#580000
0"
#585000
b1001 *
0#
0&
b1010 +
1"
#590000
0"
#595000
1"
#600000
0"
#605000
1"
#610000
0"
#615000
1"
#620000
0"
#625000
1&
1"
#630000
0"
#635000
b1000 *
b0 +
b100 ,
1#
1"
#640000
0"
#645000
b111 *
b1 +
1"
#650000
0"
#655000
b110 *
b10 +
1"
#660000
0"
#665000
b101 *
b11 +
1"
#670000
0"
#675000
b1001 *
0&
b100 +
1"
#680000
0"
#685000
b1000 *
b0 +
b101 ,
1&
1"
#690000
0"
#695000
b111 *
b1 +
1"
#700000
0"
#705000
b110 *
b10 +
1"
#710000
0"
#715000
b101 *
b11 +
1"
#720000
0"
#725000
b100 *
b100 +
1"
#730000
0"
#735000
b11 *
b101 +
1"
